Workbook

Sheet Dia Producción
E6: Fecha Producción: 07 de Septiembre 2026 | G6: Proyección Producción | H6: 230 | J6: Costos Mensual Producción
E7: Fecha Compra | F7: Insumos | G7: Factura | H7: Valor | J7: Concepto | K7: Valor
E8: 46274 | F8: Pollo | G8: 557F113735 | H8: 201000 | J8: Luz | K8: 45000
E9: 46274 | F9: Multivitaminico | G9: 552451 | H9: =(49000/350)*230 -> 32200 | J9: Agua | K9: 10000
E10: 46293 | F10: Verduras | G10: 6FE-118823 | H10: 59463 | J10: Mantenimiento | K10: 70000
E11: 46293 | F11: Higados | G11: 22FE-16778 | H11: 144260 | J11: Repuestos | K11: 70000
E12: 46294 | F12: Salvado y Avena | G12: - | H12: =3900+13600+8900 -> 26400 | J12: Arriendo | K12: 250000
E13: 46271 | F13: Compra Bolsas (3und*100 c/u) | G13: PETA-2667 POS | H13: =((13800+7500)/300)*F30 -> 17608 | J13: Costos Inversión - Retorno Inversión (Maquinas Iniciales + Empacadora+Compresor+Software) | K13: =(20000000+11000000+2000000+2000000)/120 -> 291666.67
E14: 46294 | F14: Compra carne | G14: - | H14: 80000
E15: 27-29 Septiembre 2026 | F15: Mano de Obra | G15: - | H15: 50000
G16: Total Compras | H16: =SUM(H8:H15) -> 610931
J17: Total Adicionales | K17: =SUM(K8:K16) -> 736666.67
J18: Producción Mensual | K18: =+F30+F30 -> 496
D20: 46241 | E20: Cierre Caja Anterior | F20: =+#REF! -> #REF! | J20: Cierre Caja Anterior | K20: =+#REF! -> #REF!
D21: 46268 | E21: Ingresos Efectivo | F21: 0 | J21: Ingresos Efectivo | K21: 0
D22: 46270 | E22: Cierre de Caja BOLD | F22: 0 | J22: Cierre de Caja BOLD | K22: 0
D23: 46272 | E23: Nuevo Cierre de Caja EFECTIVO | F23: =F20+F21-H16+23 -> #REF! | J23: Nuevo Cierre de Caja EFECTIVO | K23: =K20+K21-K17+23 -> #REF!
F24: =+F22+F23 -> #REF! | K24: =+K22+K23 -> #REF!
J25: Costo por Unidad de Bolsa | K25: =+K17/K18 -> 1485.2151
E26: CANTIDADES PRODUCCIÓN REAL | J26: Precio Estimado por unidad Producción + Costos Mensuales | K26: =F31+K25 -> 3948.6465
E27: Pollo | F27: =+'Ventas Comida - Inventario'!G24 -> 191
E28: Mixta | F28: =+'Ventas Comida - Inventario'!I24 -> 0
E29: Carne | F29: =+'Ventas Comida - Inventario'!H24 -> 57
E30: TOTAL | F30: =SUM(F27:F29) -> 248
E31: Precio Estimado por unidad Producción | F31: =((H16)/F30) -> 2463.4315

Sheet Ventas Comida - Inventario
E6: Fecha | F6: Detalle | G6: 5000 | H6: 7500 | I6: 6000 | J6: Valor Venta | K6: Pagado a | L6: JC | M6: =+J9+J10+J11+J12+J13+J14+J18+J15+J16+J17+#REF!+J20+J21+J23+#REF!+J24+J26+J27+J28+J30+J31+J33+J34+J36 -> #REF! | N6: BOLD | O6: =+J35 -> 0
G7: P | H7: C | I7: M | L7: AT | M7: =+J32 -> 0
E8: 46271 | F8: Inventario | G8: 202 | H8: 36 | I8: 16 | J8: --- | K8: ---
E9: 46270 | F9: Venta Susana | G9: 0 | H9: 17 | I9: 0 | J9: =(G9*$G$6)+(H9*$H$6)+(I9*$I$6) -> 127500 | K9: BOLD | L9: =+J9 -> 127500 | M9: =+M7+M6+O6 -> #REF!
E10: 46274 | F10: Venta Rene | G10: 21 | H10: 0 | I10: 0 | J10: =(G10*$G$6)+(H10*$H$6)+(I10*$I$6) -> 105000 | K10: BOLD | L10: =+J10+L9 -> 232500
E11: 46278 | F11: Consumo Jhon | G11: 21 | H11: 0 | I11: 0 | J11: =(G11*$G$5)+(H11*$H$6)+(I11*$I$6) -> 0 | K11: --- | L11: =+J11+L10 -> 232500
E12: 46279 | F12: Venta Johana Alcaldia | G12: 2 | H12: 0 | I12: 0 | J12: =(G12*$G$6)+(H12*$H$6)+(I12*$I$6) -> 10000 | K12: AT | L12: =+J12+L11 -> 242500
E13: 46280 | F13: Consumo Alvaro | G13: 21 | H13: 0 | I13: 0 | J13: =(G13*$G$5)+(H13*$H$6)+(I13*$I$6) -> 0 | K13: --- | L13: =+J13+L12 -> 242500
E14: 46281 | F14: Venta Rene | G14: 23 | H14: 0 | I14: 0 | J14: =(G14*$G$6)+(H14*$H$6)+(I14*$I$6) -> 115000 | K14: BOLD | L14: =+J14+L13 -> 357500
E15: 46286 | F15: Consumo Jhon | G15: 21 | H15: 0 | I15: 0 | J15: =(G15*$G$5)+(H15*$H$6)+(I15*$I$6) -> 0 | K15: --- | L15: =+J15+L14 -> 357500
E16: 46288 | F16: Venta Rene | G16: 21 | H16: 0 | I16: 1 | J16: =(G16*$G$6)+(H16*$H$6)+(I16*$I$5) -> 105000 | K16: BOLD | L16: =+J16+L15 -> 462500
E17: 46290 | F17: Consumo Alvaro | G17: 21 | H17: 0 | I17: 0 | J17: =(G17*$G$5)+(H17*$H$6)+(I17*$I$6) -> 0 | K17: --- | L17: =+J17+L16 -> 462500
E18: 46293 | F18: Venta Rene | G18: 21 | H18: 0 | I18: 0 | J18: =(G18*$G$6)+(H18*$H$6)+(I18*$I$6) -> 105000 | K18: BOLD | L18: =+J18+L17 -> 567500
E19: 46293 | F19: Venta Susana | G19: 0 | H19: 19 | I19: 0 | J19: =(G19*$G$6)+(H19*$H$6)+(I19*$I$6) -> 142500 | K19: BOLD | L19: =+J19+L18 -> 710000
E20: 46293 | F20: Inventario | G20: =+G8-G9-G10-G11-G12-G13-G14-G15-G16-G17-G18 -> 30 | H20: =+H8-H9-H10-H11-H12-H13-H14-H15-H16-H17-H18-H19 -> 0 | I20: =+I8-I9-I10-I11-I12-I13-I14-I15-I16-I17-I18 -> 15 | J20: =SUM(J9:J19) -> 710000 | K20: ----
E21: 46293 | F21: Consumo Jhon | G21: 21 | H21: 0 | I21: 0 | J21: 0 | K21: ---
E22: 46293 | F22: Venta Johana Alcaldia | G22: 2 | H22: 0 | I22: 0 | K22: BOLD
E23: 46294 | F23: Inventario | G23: =+G20-G21-G22 -> 7 | H23: =+H20-H21 -> 0 | I23: =I20-I21 -> 15 | J23: --- | K23: ---
E24: 46294 | F24: PRODUCCIÓN | G24: =((4*24)+4)+((3*24)+19) -> 191 | H24: =(2*24)+9 -> 57 | I24: 0 | J24: =+'Dia Producción'!H16 -> 610931 | K24: =+'Dia Producción'!F31 -> 2463.4315 | L24: Valor Producción
E25: 46294 | F25: Inventario | G25: =+G23+G24 -> 198 | H25: =+H23+H24 -> 57 | I25: =+I23+I24 -> 15
J26: =(G26*$G$6)+(H26*$H$6)+(I26*$I$6) -> 0
J27: =(G27*$G$6)+(H27*$H$6)+(I27*$I$6) -> 0
J28: =(G28*$G$6)+(H28*$H$6)+(I28*$I$6) -> 0
J29: =(G29*$G$6)+(H29*$H$6)+(I29*$I$6) -> 0
J30: =(G30*$G$6)+(H30*$H$6)+(I30*$I$6) -> 0
J31: =(G31*$G$6)+(H31*$H$6)+(I31*$I$6) -> 0
J32: =(G32*$G$6)+(H32*$H$6)+(I32*$I$6) -> 0
J33: =(G33*$G$6)+(H33*$H$6)+(I33*$I$6) -> 0
J34: =(G34*$G$6)+(H34*$H$6)+(I34*$I$6) -> 0
J35: =(G35*$G$6)+(H35*$H$6)+(I35*$I$6) -> 0
J36: =(G36*$G$6)+(H36*$H$6)+(I36*$I$6) -> 0
J37: =(G37*$G$6)+(H37*$H$6)+(I37*$I$6) -> 0
... J65: =(G65*$G$6)+(H65*$H$6)+(I65*$I$6) -> 0
J66: =SUBTOTAL(9,J9:J65) -> 2030931
